product_scraper/__init__.py
product_scraper/core.py
product_scraper/create_data/__init__.py
product_scraper/create_data/select_training_data.py
product_scraper/train_model/__init__.py
product_scraper/train_model/predict_data.py
product_scraper/train_model/process_data.py
product_scraper/train_model/train_model.py
product_scraper/utils/__init__.py
product_scraper/utils/console.py
product_scraper/utils/features.py
product_scraper/utils/utils.py
product_scraper/create_data/ui/core.js
product_scraper/create_data/ui/styles.css
product_scraper/create_data/ui/update.js
product_scraper-0.1.4.dist-info/METADATA
product_scraper-0.1.4.dist-info/WHEEL
product_scraper-0.1.4.dist-info/RECORD
