Metadata-Version: 2.4
Name: product-scraper
Version: 0.1.4
Summary: A machine-learning based web scraper for product data.
Author-email: Your Name <your.email@example.com>
License-Expression: MIT
Requires-Python: >=3.9
Requires-Dist: lxml>=4.9.0
Requires-Dist: matplotlib>=3.0.0
Requires-Dist: pandas>=1.5.0
Requires-Dist: pillow>=9.0.0
Requires-Dist: playwright>=1.30.0
Requires-Dist: pyyaml>=6.0
Requires-Dist: regex>=2022.10.31
Requires-Dist: requests>=2.28.0
Requires-Dist: rich>=13.0.0
Requires-Dist: scikit-learn>=1.2.0
Requires-Dist: seaborn>=0.11.0
Provides-Extra: dev
Requires-Dist: black; extra == 'dev'
Requires-Dist: isort; extra == 'dev'
Requires-Dist: pytest; extra == 'dev'
Requires-Dist: twine; extra == 'dev'
